catscrape/__init__.py
catscrape/data.py
catscrape/project.py
catscrape/scratcher.py
catscrape/studio.py
catscrape/web.py
catscrape-1.2.3.dist-info/METADATA
catscrape-1.2.3.dist-info/WHEEL
catscrape-1.2.3.dist-info/licenses/LICENSE
catscrape-1.2.3.dist-info/RECORD
