Metadata-Version: 2.4
Name: catscrape
Version: 1.2.3
Summary: A Python library with functions to scrape data from Scratch.mit.edu
Project-URL: Homepage, https://github.com/att131/catscrape
Project-URL: Bug Tracker, https://github.com/att131/catscrape/issues
Project-URL: Source, https://github.com/att131/catscrape
Project-URL: Documentation, https://github.com/att131/catscrape#readme
Author-email: Atticus Alarcon <atticusaalarcon@gmail.com>
License: Copyright 2025 Atticus Alarcon
License-File: LICENSE
Keywords: api,scraping,scratch,web
Classifier: License :: OSI Approved :: MIT License
Classifier: Operating System :: OS Independent
Classifier: Programming Language :: Python :: 3
Requires-Python: >=3.12
Requires-Dist: appdirs>=1.4.4
Requires-Dist: numpy>=2.3.0
Requires-Dist: requests>=2.32.4
Requires-Dist: selenium>=4.34.0
Requires-Dist: webdriver-manager>=4.0.2
